freddy_camera/__main__.py
freddy_camera/frames/fredbear/1.png
freddy_camera/frames/fredbear/2.png
freddy_camera/frames/markiplier/1.png
freddy_camera/frames/markiplier/2.png
freddy_camera/frames/markiplier/3.png
freddy_camera/frames/withered_freddy/1.png
freddy_camera/frames/withered_freddy/2.png
freddy_camera/frames/withered_freddy/3.png
freddy_camera/frames/withered_freddy/4.png
freddy_camera/frames/withered_freddy/5.png
freddy_camera/frames/withered_freddy/6.png
freddy_camera-1.3.0.dist-info/METADATA
freddy_camera-1.3.0.dist-info/WHEEL
freddy_camera-1.3.0.dist-info/RECORD
