Metadata-Version: 2.1
Name: freddy_camera
Version: 1.3.0
Summary: 
Author: megahomyak
Author-email: g.megahomyak@gmail.com
Requires-Python: >=3.8,<3.11
Classifier: Programming Language :: Python :: 3
Classifier: Programming Language :: Python :: 3.8
Classifier: Programming Language :: Python :: 3.9
Classifier: Programming Language :: Python :: 3.10
Requires-Dist: Pillow (>=10.0.0,<11.0.0)
Requires-Dist: pyvirtualcam[numpy] (==0.9.1)
Requires-Dist: sounddevice (>=0.4.6,<0.5.0)
